{
  "primary": {
    "DEFAULT": "#26754a",
    "50": "#f0f9f3",
    "100": "#daf1e0",
    "200": "#b8e2c5",
    "300": "#95d1ab",
    "400": "#58af7a",
    "500": "#36935e",
    "600": "#26754a",
    "700": "#1e5e3d",
    "800": "#1a4b31",
    "900": "#163e2a",
    "950": "#0b2317"
  },
  "secondary": {
    "DEFAULT": "#c4986f",
    "50": "#faf6f2",
    "100": "#f3ece1",
    "200": "#e6d6c2",
    "300": "#d6bb9b",
    "400": "#c4986f",
    "500": "#b98256",
    "600": "#ab6f4b",
    "700": "#8f593f",
    "800": "#744938",
    "900": "#5e3d30",
    "950": "#321f18"
  },
  "neutral": {
    "DEFAULT": "#eeeced",
    "900": "#322d2f",
    "800": "#65595f",
    "700": "#95888e",
    "600": "#c2babe",
    "500": "#eeeced",
    "400": "#f2f0f1",
    "300": "#f5f4f4",
    "200": "#f8f7f8",
    "100": "#fcfbfb"
  }
}